{
  "agenda_identifier": "agenda_20240118_special",
  "agenda_number": 20240118,
  "source_file": "agenda_20240118_special.txt",
  "summary": "**Meeting Overview**:  \nThe City of Dallas is holding a special called meeting of the Housing and Homelessness Solutions Committee on January 18, 2024, at 6:00 PM. The primary purpose of this meeting is to discuss the Homelessness, Organizations, Policies, and Encampments (H.O.P.E.) report, which addresses strategies and policies related to homelessness in Dallas.\n\n**Key Agenda Items**:  \n1. **Briefing on H.O.P.E. Report**: An overview of the findings and recommendations from the H.O.P.E. report will be presented.\n2. **Discussion of H.O.P.E. Report**: Committee members will engage in a dialogue regarding the implications and actions stemming from the report.\n3. **Closed Session**: A legal briefing will be held to seek advice from the city attorney concerning the H.O.P.E. report.\n\n**Important Details**:  \nThe meeting will include public comments on the H.O.P.E. report, allowing community input on the discussed topics. The closed session may involve discussions related to potential litigation, property negotiations, or personnel matters, as outlined by Texas Open Meetings Act provisions.\n\n**Action Items**:  \nThe committee will seek to make decisions based on the H.O.P.E. report findings, including potential policy changes or initiatives to address homelessness. Approval for any proposed actions or recommendations from the report may also be sought during the meeting.",
  "original_length": 4986,
  "summary_length": 1387,
  "processed_at": "262759.4165605"
}