{
  "agenda_identifier": "agenda_20240805_hearing",
  "agenda_number": 20240805,
  "source_file": "agenda_20240805_hearing.txt",
  "summary": "**Meeting Overview**:  \nThe Dallas Landmark Commission will hold a regular meeting on August 5, 2024, with a briefing at 10:00 A.M. and a public hearing at 1:00 P.M. at Dallas City Hall. The meeting aims to discuss various historic preservation matters, including Certificates of Appropriateness and eligibility for tax exemptions.\n\n**Key Agenda Items**:  \n1. Approval of minutes from the July 1, 2024, meeting.\n2. Updates on the First Baptist Church property fire and other staff reports.\n3. Public hearing on multiple Certificates of Appropriateness for various properties within historic districts.\n\n**Important Details**:  \n- Proposals include requests for Certificates of Appropriateness for renovations and restorations in historic districts, such as replacing windows, constructing ramps, and painting structures.\n- Significant items include a request for a historic designation process for Reverchon Park and a hearing for a historic overlay for the Belmont Motor Hotel.\n\n**Action Items**:  \n- Decisions are sought on multiple Certificates of Appropriateness, including:\n  - Approval for tax exemption and rehabilitation expenditures for properties in the Tenth Street Historic District.\n  - Various requests for alterations and restorations across several historic districts, with staff recommendations for approval or denial based on preservation criteria.\n- The Commission will also consider the initiation of the historic designation process for Reverchon Park and the Belmont Motor Hotel's historic overlay.\n\nThe meeting will accommodate public participation, and individuals wishing to speak must register in advance.",
  "original_length": 64767,
  "summary_length": 1631,
  "processed_at": "286221.256063666"
}