{
  "agenda_identifier": "agenda_20240220_council",
  "agenda_number": 20240220,
  "source_file": "agenda_20240220_council.txt",
  "summary": "**Meeting Overview**:  \nThe Charter Review Commission of the City of Dallas will convene on February 20, 2024, at 6:30 PM, both in-person at City Hall and via video conference. The meeting aims to discuss proposed amendments to the city charter, focusing on governance structure and election processes.\n\n**Key Agenda Items**:  \n1. Approval of previous meeting minutes.\n2. Staff and commissioner briefings on City Council composition, term lengths, and election dates.\n3. Consideration of proposed amendments regarding the city’s government structure, council size, appointment processes, and term lengths.\n\n**Important Details**:  \n- Proposals include changing from a Council-Manager to a Mayor-Council form of government, altering council size (options range from 15 to 20 members), and modifying the election date from May to November.\n- Discussions will also cover the potential abolition or amendment of the mayor pro tem positions, staggering council terms, and aligning terms for municipal judges and board members with council terms.\n\n**Action Items**:  \nThe Commission seeks to approve or reject various amendments, including:\n- Changing the government structure.\n- Expanding the council size.\n- Adjusting the election date.\n- Modifying term lengths for council members.\n- Staggering council terms and aligning terms for judges and board members.\n\nThe meeting will also include an executive session if necessary for legal or personnel matters. Public participation is encouraged through both in-person and virtual attendance.",
  "original_length": 14054,
  "summary_length": 1533,
  "processed_at": "283430.333706166"
}