{
  "agenda_number": 475,
  "source_file": "Agenda_475.txt",
  "summary": "**Meeting Overview:**\nThe Dallas City Council will convene on April 10, 2024, at 9:00 AM in the Council Chambers at City Hall, with an option for virtual attendance. This regular meeting aims to address various city governance matters, including budget approvals, policy changes, and public hearings.\n\n**Key Agenda Items:**\n1. Approval of minutes from the March 27, 2024, City Council meeting.\n2. Consent agenda items (2-35) covering settlements, ordinance amendments, and service contracts.\n3. Individual consideration items (36-37) related to board appointments and the annual adoption of the City’s Investment Policy.\n4. Zoning cases (Z1-Z5) involving amendments to specific use permits and mixed-use district designations.\n5. Public hearings (PH1-PH2) on the Historic and Cultural Preservation Strategy and an appeal regarding a development plan amendment.\n\n**Important Details:**\n- A significant item includes a settlement with Atlantic Specialty Insurance for $4.33 million related to construction failures.\n- Amendments to the Dallas City Code regarding emergency vehicle operations and transportation-for-hire rates are proposed.\n- A grant acceptance from the U.S. Department of Justice for $1.27 million to enhance crime prevention efforts is on the agenda.\n\n**Action Items:**\nThe Council seeks approval for various contracts, including a $722,255 consulting service contract for zoning assistance and a $1.22 million land acquisition for the West Dallas Gateway Project. Additionally, they will vote on the adoption of the Historic and Cultural Preservation Strategy and the annual investment policy.",
  "original_length": 68308,
  "summary_length": 1610,
  "processed_at": "187691.679102"
}