{
  "agenda_number": 271,
  "source_file": "Agenda_271.txt",
  "summary": "**Meeting Overview**:  \nThe City Plan Commission of Dallas will convene on September 19, 2024, for a briefing at 9:00 AM followed by a public hearing at 12:30 PM. The meeting will take place both via videoconference and in the Council Chambers at City Hall. The primary purpose is to discuss various zoning cases, development code amendments, and subdivision applications.\n\n**Key Agenda Items**:  \nThe agenda includes several significant zoning cases for approval, including applications for multifamily districts, amendments to specific use permits, and the establishment of new planned development districts. Key items also involve under advisement zoning cases and development code amendments.\n\n**Important Details**:  \nNotable proposals include:\n- **Zoning Cases**: Multiple applications for zoning changes to multifamily and mixed-use districts, with staff recommendations generally favoring approval.\n- **Development Code Amendments**: Consideration of amendments to define \"private game club\" and establish related zoning standards.\n- **Special Provision Sign District**: Proposal to create \"The Frontier Subdistrict\" with specific operational hours for signage.\n\n**Action Items**:  \nThe Commission seeks approvals on various zoning cases (Items 1-9), including consent items and those under advisement (Items 10-14). Additionally, they will consider amendments to the development code (Item 17) and the establishment of a new sign district (Item 18). The meeting will also address appointments to CPC committees. Public testimony will be allowed, requiring prior registration.",
  "original_length": 43529,
  "summary_length": 1584,
  "processed_at": "183251.221819583"
}