{
  "agenda_identifier": "agenda_20240325_budget_01",
  "agenda_number": 20240325,
  "source_file": "agenda_20240325_budget_01.txt",
  "summary": "**Meeting Overview**:  \nThe Housing and Homelessness Solutions Committee of the Dallas City Council will convene on March 25, 2024, at 9:00 AM, both in-person at City Hall and via video conference. The meeting aims to address key issues related to housing and homelessness solutions in Dallas.\n\n**Key Agenda Items**:  \n1. Approval of minutes from previous meetings.\n2. Quarterly report on the Homeless Response System.\n3. Discussion on options and next steps for the property at 2929 South Hampton Road.\n4. Updates on various housing development programs and properties.\n\n**Important Details**:  \n- The committee will review the performance measures for the Department of Housing & Neighborhood Revitalization for FY 2022-23.\n- A significant proposal includes the recommendation for the City Council to consider the sale of a land transfer program lot to South Fair Community Development Corporation.\n- Updates will be provided on the 1,000 Unit Challenge and temporary housing solutions.\n\n**Action Items**:  \n- Approval of the minutes from the January meetings.\n- Recommendations for the City Council regarding the sale of land and upcoming amendments to housing programs.\n- Discussion on upcoming agenda items, including a service contract for encampment clean-up and a public hearing for reprogramming CDBG funds.\n\nThe meeting will be broadcast live, and public participation is encouraged.",
  "original_length": 24851,
  "summary_length": 1393,
  "processed_at": "263769.467908"
}