{
  "agenda_identifier": "agenda_20240528_council",
  "agenda_number": 20240528,
  "source_file": "agenda_20240528_council.txt",
  "summary": "**Meeting Overview**:  \nThe Ad Hoc Committee on Legislative Affairs of the City of Dallas is convening on May 28, 2024, at 9:00 AM. The meeting will be held both via videoconference and in-person at City Hall, allowing public attendance through both formats. The primary purpose is to discuss legislative priorities and review previous meeting minutes.\n\n**Key Agenda Items**:  \n1. Approval of the minutes from the May 7, 2024, meeting (Item 24-1775).\n2. Consideration of the 2025 State Legislative Priorities, presented by Clifford Sparks, State Legislative Director (Item 24-1780).\n\n**Important Details**:  \nThe meeting will focus on establishing the City’s legislative priorities for the upcoming year, which is crucial for guiding the city's advocacy efforts at the state level. The presentation will likely outline key issues and initiatives that the committee believes should be prioritized in legislative discussions.\n\n**Action Items**:  \nThe committee is seeking approval of the minutes from the previous meeting and will discuss and potentially approve the proposed 2025 State Legislative Priorities. Additionally, there is a possibility of entering an executive session to discuss sensitive matters related to litigation, property negotiations, or personnel evaluations, should those topics arise during the meeting.",
  "original_length": 5011,
  "summary_length": 1325,
  "processed_at": "285442.488660791"
}