{
  "agenda_number": 114,
  "source_file": "Agenda_114.txt",
  "summary": "**Meeting Overview**:  \nThe City of Dallas Community Police Oversight Board (CPOB) will hold a regular meeting on January 14, 2025, at 5:30 PM. The meeting aims to address community concerns regarding police oversight, present updates on departmental activities, and facilitate public engagement.\n\n**Key Agenda Items**:  \n1. Call to Order & Roll Call  \n2. Public Comment/Open Microphone  \n3. Approval of December 10, 2024, meeting minutes  \n4. Introduction of Dallas Police Department Interim Chief Michael Igo  \n5. Presentation on racial disparities in DPD arrests  \n6. Overview of the OCPO Accountability and Transparency Dashboard  \n7. Reports from OCPO staff, including legislative updates and independent review requests  \n\n**Important Details**:  \n- A presentation by Bob Scales will analyze racial disparities in arrests by council district using data from various sources.  \n- The OCPO will showcase a new Transparency & Accountability Dashboard designed to enhance public trust by detailing complaint statistics and resolutions.  \n- Legislative updates will include discussions on Senate Bills 280 and 281, with recommendations for the complaint intake process.\n\n**Action Items**:  \n- Approval of the December meeting minutes.  \n- Votes on independent reviews of specific cases (EC2024-1186, EC2024-0675, CN2024-138).  \n- Approval of the CPOB Annual Report due by February 1.  \n\nThe meeting will allow public participation, with registration required for those wishing to speak.",
  "original_length": 21706,
  "summary_length": 1487,
  "processed_at": "170410.035981916"
}