{
  "agenda_identifier": "agenda_20240307_hearing",
  "agenda_number": 20240307,
  "source_file": "agenda_20240307_hearing.txt",
  "summary": "**Meeting Overview**:  \nThe City Plan Commission of Dallas will hold a meeting on March 7, 2024, featuring a briefing at 9:00 AM and a public hearing starting at 12:30 PM. The meeting aims to discuss various development and zoning cases, as well as to approve minutes from previous meetings.\n\n**Key Agenda Items**:  \nThe agenda includes briefings on the ForwardDallas Comprehensive Land Use Plan, approval of minutes from past meetings, and multiple action items related to development plans and zoning cases. Key items include consent and under advisement zoning cases, subdivision applications, and residential replats.\n\n**Important Details**:  \nSignificant proposals include development plans for properties within Planned Development Districts, amendments to specific use permits for various establishments (e.g., schools, community service centers, and alcoholic beverage establishments), and applications for new zoning districts. Notable cases involve a public school on an R-7.5(A) Single Family District and a community service center in a CR-D-1 Community Retail District.\n\n**Action Items**:  \nThe Commission seeks approval for various development plans, zoning amendments, and subdivision applications. Specific decisions include approving development plans for properties in Victory Planned Development District and amendments to specific use permits for establishments like microbreweries and schools. Additionally, the Commission will consider authorizing a public hearing to determine appropriate zoning for a designated area encompassing several neighborhoods.\n\nThis meeting will provide a platform for public input and decision-making on critical urban development issues in Dallas.",
  "original_length": 57806,
  "summary_length": 1699,
  "processed_at": "263591.50034375"
}