{
  "agenda_number": 605,
  "source_file": "Agenda_605.txt",
  "summary": "**Meeting Overview**:  \nThe Dallas Veteran’s Affairs Commission will hold a regular meeting on January 11, 2024, at 12:00 P.M. in the Dallas City Hall, 6ES Council Briefing Room, with an option for videoconference participation. The purpose of the meeting is to discuss and approve the FY 2023 Annual Report and address public comments.\n\n**Key Agenda Items**:  \n1. Call to Order & Pledge of Allegiance  \n2. Public Comments on agenda items III - VI  \n3. Approval of minutes from the December 14, 2023 meeting  \n4. Review and discussion of the draft FY 2023 Annual Report  \n5. Vote to approve the FY 2023 Annual Report  \n6. Announcements regarding the timeline for the Annual Report  \n\n**Important Details**:  \nThe meeting will include a review of the FY 2023 Annual Report, allowing for final feedback and discussion before the vote for approval. Public comments will be welcomed on the report and other agenda items. The meeting will ensure compliance with accessibility standards, offering accommodations for those needing assistance.\n\n**Action Items**:  \nThe Commission seeks approval of the meeting minutes from December 14, 2023, and a vote to approve the FY 2023 Annual Report. Additionally, public participation is encouraged, with registration required 24 hours in advance for those wishing to speak.",
  "original_length": 8180,
  "summary_length": 1307,
  "processed_at": "190085.659310708"
}