{
  "agenda_identifier": "agenda_20240327_council",
  "agenda_number": 20240327,
  "source_file": "agenda_20240327_council.txt",
  "summary": "**Meeting Overview**:  \nThe City of Dallas City Council will convene on March 27, 2024, at 9:00 AM in the Council Chambers, 6th Floor, City Hall. This regular meeting aims to discuss various city matters, including budget approvals, policy changes, and zoning regulations.\n\n**Key Agenda Items**:  \nThe agenda includes the approval of minutes from previous meetings, a consent agenda with items 2-36, and individual consideration items 37-44. Public hearings will occur for zoning cases and budget discussions.\n\n**Important Details**:  \nSignificant proposals include:\n- **Budget Items**: Approval for the issuance of General Obligation Refunding and Improvement Bonds (up to $410 million) and Certificates of Obligation (up to $218 million) to fund various city projects.\n- **Policy Changes**: Amendments to the Dallas Housing Resource Catalog and updates to the Economic Development Incentive Policy.\n- **Projects**: Contracts for construction services, including improvements to sidewalks and barrier-free ramps, and the acquisition of land for the Dallas Floodway Extension Project.\n\n**Action Items**:  \nThe Council seeks to approve multiple financial agreements, including settlements for lawsuits, engineering contracts, and budget amendments. Public hearings will also address zoning changes and the use of parkland for utility projects. The Council will consider appointments to boards and commissions and evaluate sanctions against a former employee related to ethics violations. \n\nOverall, the meeting will focus on financial decisions, community development, and regulatory approvals essential for city operations.",
  "original_length": 113072,
  "summary_length": 1623,
  "processed_at": "284232.125017583"
}