{
  "agenda_identifier": "agenda_20250128_special_01",
  "agenda_number": 20250128,
  "source_file": "agenda_20250128_special_01.txt",
  "summary": "**Meeting Overview**:  \nThe Housing and Homelessness Solutions Committee of the City of Dallas is convening a special called meeting on January 28, 2025, at 9:00 AM. The meeting will be held both in-person at the Council Chambers and virtually via video conference. The primary purpose is to discuss updates and proposals related to housing and homelessness initiatives in Dallas.\n\n**Key Agenda Items**:  \n1. Approval of minutes from the December 10, 2024, meeting.\n2. Briefing on the acquisition of CitySquare by The Stewpot.\n3. Overview of the Street to Home Initiative.\n4. Updates on various properties managed by the Office of Homeless Solutions and the Department of Housing and Community Development.\n5. Discussion on recommended changes to policies and bylaws for the Dallas Housing Finance Corporation and the Dallas Public Facility Corporation.\n\n**Important Details**:  \n- The meeting will include presentations on the Stewpot acquisition and the Street to Home Initiative, aimed at improving homelessness solutions.\n- An update on the Department of Housing and Community Development's five-year housing production needs will be provided.\n- Upcoming agenda items for the City Council include resolutions to support applications for Low Income Housing Tax Credits (LIHTC) for multiple affordable housing developments.\n\n**Action Items**:  \nThe committee will seek approval for the minutes from the previous meeting and will discuss and potentially endorse several proposals related to housing initiatives, including support for LIHTC applications and policy changes for housing finance entities.",
  "original_length": 24575,
  "summary_length": 1602,
  "processed_at": "268306.185594125"
}