{
  "agenda_identifier": "agenda_20241209_budget_01",
  "agenda_number": 20241209,
  "source_file": "agenda_20241209_budget_01.txt",
  "summary": "**Meeting Overview**:  \nThe Public Safety Committee of the Dallas City Council will convene on December 9, 2024, at 1:00 PM in the Council Chambers, City Hall. The meeting aims to discuss various public safety initiatives, updates, and funding proposals related to police and fire services.\n\n**Key Agenda Items**:  \nThe meeting will include discussions on police and fire recruiting and retention, updates on the Violent Crime Reduction Plan, and an overview of the Crisis Response Division. Additional briefings will cover wellness programs for police and fire personnel, updates on Dallas Fire-Rescue EMS, and the introduction of personal delivery devices.\n\n**Important Details**:  \nSignificant proposals include the acceptance of multiple grants aimed at combating internet crimes against children, totaling over $1.2 million, and funding for the Dallas Police Department’s safety initiatives. A notable item is the proposed acquisition of a new Fire Station Alerting System, with a total cost of approximately $4.55 million, funded through the ARPA Redevelopment Fund.\n\n**Action Items**:  \nThe committee will seek approval for various funding applications, including a $925,369 grant from the DOJ for internet crimes, a $506,102 grant from the U.S. Department of Transportation for commercial vehicle safety, and a $5.84 million grant from the Department of Homeland Security for preparedness against terrorist attacks. Additionally, the committee will vote on the appointment of municipal judges and the establishment of their salaries. \n\nThis meeting presents a critical opportunity for the committee to enhance public safety resources and address pressing community needs.",
  "original_length": 32681,
  "summary_length": 1679,
  "processed_at": "267504.616053583"
}