{
  "agenda_identifier": "agenda_20240228_council",
  "agenda_number": 20240228,
  "source_file": "agenda_20240228_council.txt",
  "summary": "**Meeting Overview**:  \nThe City of Dallas City Council will convene on February 28, 2024, at 9:00 AM in the Council Chambers, City Hall. This is a regular council meeting intended to discuss and vote on various agenda items, including budget amendments, zoning cases, and public hearings.\n\n**Key Agenda Items**:  \n1. **Approval of Minutes** from the previous meeting.\n2. **Consent Agenda**: Includes budget amendments, contract approvals, and ordinances related to city operations.\n3. **Public Hearings**: Scheduled for zoning changes and budget reprogramming, including the adoption of substantial amendments to the FY 2023-24 Action Plan for Community Development Block Grant funds.\n\n**Important Details**:  \n- A significant proposal involves amending the franchise agreement with Oncor Electric, projected to generate $50 million annually for the General Fund.\n- The council will consider a $1.78 million TIF development agreement for the Lancaster-Corning Retail Development Project.\n- Public hearings will address the use of funds for the Emergency Rental Assistance Program and amendments to the Deep Ellum TIF District budget.\n\n**Action Items**:  \n- The council seeks approval for various budget amendments and contracts, including a $7.6 million architectural services contract for the Cotton Bowl renovation.\n- Approval of a joint elections agreement for a special election on May 4, 2024, with a total estimated cost of $745,279.67.\n- Decisions on zoning amendments affecting multiple districts and public hearings on significant budget reallocations.\n\nThis meeting will also include opportunities for public comment and discussion on various city initiatives and projects.",
  "original_length": 104179,
  "summary_length": 1684,
  "processed_at": "283693.716304166"
}