{
  "agenda_number": 282,
  "source_file": "Agenda_282.txt",
  "summary": "**Meeting Overview**:  \nThe City of Dallas City Council will convene for a regular meeting on September 11, 2024, at 9:00 AM in the Council Chambers, City Hall. The meeting will be accessible both in-person and via videoconference. The primary purpose is to discuss various agenda items, including approvals for contracts, budget allocations, and zoning matters.\n\n**Key Agenda Items**:  \nThe agenda includes a consent agenda with items ranging from construction contracts for airport signage and HVAC systems to amendments in animal control ordinances. Significant zoning cases are scheduled for public hearings, addressing new subdistricts and specific use permits for various developments.\n\n**Important Details**:  \n- **Budget Items**: Notable financial proposals include a $22 million agreement for construction over Interstate Highway 30, a $12 million federal grant for airport improvements, and multiple contracts for emergency services related to severe weather.\n- **Policy Changes**: Amendments to the Dallas City Code regarding animal ownership requirements and speed regulations on roadways are also on the agenda.\n- **Zoning Proposals**: Several public hearings will consider new zoning subdistricts and specific use permits, including a child-care facility and a restaurant with drive-through service.\n\n**Action Items**:  \nThe Council will seek approvals for numerous contracts and agreements, including:\n- A construction service contract for the Dallas Airport System.\n- Amendments to existing leases and service contracts for various city departments.\n- Endorsements for Councilmember appointments and funding agreements for homeless assistance services.\n- Zoning changes and public hearings on proposed developments.\n\nOverall, the meeting will address critical infrastructure, community services, and regulatory changes impacting the City of Dallas.",
  "original_length": 95893,
  "summary_length": 1864,
  "processed_at": "183416.654325125"
}