{
  "agenda_identifier": "agenda_20240502_planning",
  "agenda_number": 20240502,
  "source_file": "agenda_20240502_planning.txt",
  "summary": "**Meeting Overview**:  \nThe Dallas Community Development Commission (CDC) will hold its monthly meeting on May 2, 2024, at 6:00 PM at Dallas City Hall, Conference Room 6ES, with a videoconference option available. The purpose of the meeting is to discuss community development initiatives, review budget proposals, and facilitate public participation.\n\n**Key Agenda Items**:  \n1. Call to Order and Roll Call  \n2. Public Speakers  \n3. Approval of April 2024 Meeting Minutes  \n4. Community Development Division Report, including updates on the City Manager’s Proposed FY 2024-25 HUD Consolidated Plan Budget  \n5. Chair’s Report with updates on the 2024 Community Development Tour  \n6. Vice Chair’s Report  \n7. Public Speakers  \n8. Announcements  \n\n**Important Details**:  \nThe meeting will include a staff update on the proposed budget from the U.S. Department of Housing and Urban Development (HUD) and potential changes to committee assignments. There will also be discussions on future agenda items and community development initiatives.\n\n**Action Items**:  \nThe commission will seek approval for the minutes from the previous meeting and will discuss the proposed budget for the upcoming fiscal year. Public input will be encouraged, and individuals wishing to speak must register in advance. The meeting may also include an executive session to discuss legal and personnel matters if necessary.",
  "original_length": 13266,
  "summary_length": 1397,
  "processed_at": "284867.912568583"
}