{
  "agenda_identifier": "agenda_20250106_council",
  "agenda_number": 20250106,
  "source_file": "agenda_20250106_council.txt",
  "summary": "**Meeting Overview**:  \nThe Ad Hoc Committee on Legislative Affairs of the City of Dallas will convene on January 6, 2025, at 12:00 PM, both via videoconference and in-person at the Council Briefing Room, 6ES, City Hall. The primary purpose of the meeting is to review and discuss legislative priorities and assignments for councilmembers.\n\n**Key Agenda Items**:  \n1. Approval of the minutes from the previous meeting held on August 27, 2024.\n2. A review of legislative priorities, including recommendations for the addition or removal of items for City Council consideration.\n3. Discussion regarding legislative testimony assignments for councilmembers.\n\n**Important Details**:  \nThe meeting will include a presentation by James Anderson, Director of the Office of Government Affairs, and Bart Bevers, Inspector General of the Office of the Inspector General. The agenda may also involve an executive session to discuss sensitive matters, including pending litigation, real property negotiations, and personnel evaluations.\n\n**Action Items**:  \nThe committee will seek approval of the previous meeting's minutes and will consider recommendations regarding legislative priorities. Additionally, decisions on testimony assignments for councilmembers will be made. Public attendance is encouraged, with options for both virtual and in-person participation.",
  "original_length": 5382,
  "summary_length": 1354,
  "processed_at": "267775.2591265"
}