{
  "agenda_identifier": "agenda_20231211_regular_01",
  "agenda_number": 20231211,
  "source_file": "agenda_20231211_regular_01.txt",
  "summary": "**Meeting Overview**:  \nThe Farmers Market TIF District Board of Directors is convening for a regular meeting on December 11, 2023, at 11:00 a.m. at Dallas City Hall, with a videoconference option available. The meeting aims to review past records, annual reports, and establish a meeting schedule for the upcoming year.\n\n**Key Agenda Items**:  \n1. Introduction of participants and public comments.\n2. Review and approval of the Meeting Record from December 12, 2022.\n3. Review and approval of the Farmers Market TIF District Annual Report for FY 2022-2023.\n4. Establishment of a regular meeting schedule for 2024.\n\n**Important Details**:  \n- The Annual Report for FY 2022-2023 will be presented by Dorcy Clark, District Manager, Office of Economic Development, and requires approval to be forwarded to the City Council.\n- The meeting will also establish a regular schedule for the Board's meetings in 2024, ensuring consistent oversight and planning for the TIF District.\n\n**Action Items**:  \nThe Board is seeking approval for the Meeting Record, the Annual Report, and the proposed 2024 meeting schedule. Additionally, public comments will be solicited on agenda items 3 through 5, allowing for community input before decisions are made.",
  "original_length": 10549,
  "summary_length": 1239,
  "processed_at": "262186.91787225"
}