{
  "agenda_identifier": "agenda_20241203_budget_01",
  "agenda_number": 20241203,
  "source_file": "agenda_20241203_budget_01.txt",
  "summary": "**Meeting Overview**:  \nThe Quality of Life, Arts, and Culture Committee of the City of Dallas will convene on December 3, 2024, at 9:00 AM in the Council Chambers, City Hall. The meeting will be accessible both in-person and via video conference, aiming to discuss various cultural and community initiatives.\n\n**Key Agenda Items**:  \n1. Approval of the minutes from the November 12, 2024, meeting.\n2. Briefings on national trends in multi-use library facilities and updates on the city-owned non-commercial radio station, WRR Radio/KERA.\n3. Discussion of updated funding allocations for the Dallas Black Dance Theatre and an update on the Kalita Humphreys Theater.\n\n**Important Details**:  \n- The committee will review a funding recommendation of $248,435 for the Dallas Black Dance Theatre, contingent on the outcomes of ongoing labor disputes.  \n- The Kalita Humphreys Theater management agreement is proposed to be extended through September 30, 2028, allowing for sufficient planning and operational continuity for theater groups.\n\n**Action Items**:  \n- Approval of the meeting minutes from November 12, 2024.  \n- Consideration of the funding allocation for the Dallas Black Dance Theatre, with the recommendation to approve pending labor dispute outcomes.  \n- Discussion and potential approval of the extension of the management agreement for the Kalita Humphreys Theater.  \n\nThis meeting will address significant cultural funding and operational strategies, ensuring the continuity and enhancement of arts and culture initiatives in Dallas.",
  "original_length": 113886,
  "summary_length": 1547,
  "processed_at": "288443.281677916"
}