{
  "agenda_identifier": "agenda_20240827_budget",
  "agenda_number": 20240827,
  "source_file": "agenda_20240827_budget.txt",
  "summary": "**Meeting Overview**:  \nThe Public Safety Committee of the Dallas City Council will convene on August 27, 2024, at 9:00 AM in the Council Chambers, City Hall. The meeting aims to discuss various public safety initiatives, updates, and proposals relevant to the Dallas community.\n\n**Key Agenda Items**:  \n1. Approval of the minutes from the June 10, 2024 meeting.\n2. Updates on public safety recruiting and retention, violent crime reduction, and the Dallas Fire-Rescue 2023 Annual Report.\n3. Discussion on the Dallas Police Department's racial profiling report and violent crime clearance rates.\n4. Review of the Overdose Program and public safety dashboards.\n\n**Important Details**:  \n- A proposal to honor fallen first responders with street toppers is set for discussion, with no cost to the city.\n- The adoption of the City of Dallas Hazard Mitigation Plan is necessary for maintaining eligibility for federal funding.\n- A service contract for Deaf Link’s Accessible Hazard Alert System is proposed, totaling $352,755.\n- A grant from the Cities for Financial Empowerment Fund for $150,000 aims to enhance financial stability for low-income households.\n\n**Action Items**:  \nThe committee seeks approval for several items, including:\n- A three-year service contract for interpretation services totaling approximately $1 million.\n- An Interlocal Agreement with Southern Methodist University for a Virtual Reality De-escalation Initiative.\n- A five-year master agreement for a Law Enforcement Monitoring Facility product.\n- An Interlocal Agreement with Tarrant County for forensic analysis services.\n\nThe meeting will also include an executive session to discuss legal and personnel matters if necessary.",
  "original_length": 29496,
  "summary_length": 1704,
  "processed_at": "265942.34142175"
}